odoo/addons/shopinvader_product_stock_forecast/README.rst
odoo/addons/shopinvader_product_stock_forecast/__init__.py
odoo/addons/shopinvader_product_stock_forecast/__manifest__.py
odoo/addons/shopinvader_product_stock_forecast/i18n/shopinvader_product_stock_forecast.pot
odoo/addons/shopinvader_product_stock_forecast/models/__init__.py
odoo/addons/shopinvader_product_stock_forecast/models/shopinvader_backend.py
odoo/addons/shopinvader_product_stock_forecast/models/shopinvader_variant.py
odoo/addons/shopinvader_product_stock_forecast/readme/CONFIGURE.rst
odoo/addons/shopinvader_product_stock_forecast/readme/CONTRIBUTORS.rst
odoo/addons/shopinvader_product_stock_forecast/readme/DESCRIPTION.rst
odoo/addons/shopinvader_product_stock_forecast/readme/ROADMAP.rst
odoo/addons/shopinvader_product_stock_forecast/static/description/index.html
odoo/addons/shopinvader_product_stock_forecast/tests/__init__.py
odoo/addons/shopinvader_product_stock_forecast/tests/common.py
odoo/addons/shopinvader_product_stock_forecast/tests/test_product.py
odoo/addons/shopinvader_product_stock_forecast/views/shopinvader_backend.xml
odoo14_addon_shopinvader_product_stock_forecast-14.0.1.0.1.dev4.dist-info/METADATA
odoo14_addon_shopinvader_product_stock_forecast-14.0.1.0.1.dev4.dist-info/WHEEL
odoo14_addon_shopinvader_product_stock_forecast-14.0.1.0.1.dev4.dist-info/top_level.txt
odoo14_addon_shopinvader_product_stock_forecast-14.0.1.0.1.dev4.dist-info/RECORD
